odoo/addons/report_xlsx/README.rst
odoo/addons/report_xlsx/__init__.py
odoo/addons/report_xlsx/__manifest__.py
odoo/addons/report_xlsx/controllers/__init__.py
odoo/addons/report_xlsx/controllers/main.py
odoo/addons/report_xlsx/demo/report.xml
odoo/addons/report_xlsx/i18n/de.po
odoo/addons/report_xlsx/i18n/es.po
odoo/addons/report_xlsx/i18n/fr.po
odoo/addons/report_xlsx/i18n/hr.po
odoo/addons/report_xlsx/i18n/hr_HR.po
odoo/addons/report_xlsx/i18n/it.po
odoo/addons/report_xlsx/i18n/nl_NL.po
odoo/addons/report_xlsx/i18n/pt_PT.po
odoo/addons/report_xlsx/i18n/report_xlsx.pot
odoo/addons/report_xlsx/i18n/tr.po
odoo/addons/report_xlsx/models/__init__.py
odoo/addons/report_xlsx/models/ir_report.py
odoo/addons/report_xlsx/report/__init__.py
odoo/addons/report_xlsx/report/report_partner_xlsx.py
odoo/addons/report_xlsx/report/report_xlsx.py
odoo/addons/report_xlsx/static/description/icon.png
odoo/addons/report_xlsx/static/src/js/report/qwebactionmanager.js
odoo/addons/report_xlsx/tests/__init__.py
odoo/addons/report_xlsx/tests/test_report.py
odoo/addons/report_xlsx/views/webclient_templates.xml
odoo11_addon_report_xlsx-11.0.1.0.6.dist-info/METADATA
odoo11_addon_report_xlsx-11.0.1.0.6.dist-info/WHEEL
odoo11_addon_report_xlsx-11.0.1.0.6.dist-info/top_level.txt
odoo11_addon_report_xlsx-11.0.1.0.6.dist-info/RECORD
